setup.cfg
setup.py
pandaecs/__init__.py
pandaecs/version.py
pandapay.egg-info/PKG-INFO
pandapay.egg-info/SOURCES.txt
pandapay.egg-info/dependency_links.txt
pandapay.egg-info/requires.txt
pandapay.egg-info/top_level.txt